validations_libs/__init__.py
validations_libs/ansible.py
validations_libs/constants.py
validations_libs/exceptions.py
validations_libs/group.py
validations_libs/logger.py
validations_libs/utils.py
validations_libs/validation.py
validations_libs/validation_actions.py
validations_libs/validation_logs.py
validations_libs/callback_plugins/__init__.py
validations_libs/callback_plugins/vf_fail_if_no_hosts.py
validations_libs/callback_plugins/vf_http_json.py
validations_libs/callback_plugins/vf_validation_json.py
validations_libs/callback_plugins/vf_validation_output.py
validations_libs/callback_plugins/vf_validation_stdout.py
validations_libs/cli/__init__.py
validations_libs/cli/app.py
validations_libs/cli/base.py
validations_libs/cli/colors.py
validations_libs/cli/common.py
validations_libs/cli/community.py
validations_libs/cli/constants.py
validations_libs/cli/file.py
validations_libs/cli/history.py
validations_libs/cli/lister.py
validations_libs/cli/parseractions.py
validations_libs/cli/run.py
validations_libs/cli/show.py
validations_libs/community/__init__.py
validations_libs/community/init_validation.py
validations_libs/tests/__init__.py
validations_libs/tests/fakes.py
validations_libs/tests/test_ansible.py
validations_libs/tests/test_group.py
validations_libs/tests/test_logger.py
validations_libs/tests/test_utils.py
validations_libs/tests/test_validation.py
validations_libs/tests/test_validation_actions.py
validations_libs/tests/test_validation_log.py
validations_libs/tests/test_validation_logs.py
validations_libs/tests/callback_plugins/__init__.py
validations_libs/tests/callback_plugins/fakes.py
validations_libs/tests/callback_plugins/test_vf_fail_if_no_hosts.py
validations_libs/tests/callback_plugins/test_vf_http_json.py
validations_libs/tests/callback_plugins/test_vf_validation_json.py
validations_libs/tests/callback_plugins/test_vf_validation_output.py
validations_libs/tests/callback_plugins/test_vf_validation_stdout.py
validations_libs/tests/cli/__init__.py
validations_libs-1.9.0.dist-info/AUTHORS
validations_libs-1.9.0.dist-info/LICENSE
validations_libs-1.9.0.dist-info/METADATA
validations_libs-1.9.0.dist-info/WHEEL
validations_libs-1.9.0.dist-info/entry_points.txt
validations_libs-1.9.0.dist-info/pbr.json
validations_libs-1.9.0.dist-info/top_level.txt
validations_libs-1.9.0.dist-info/RECORD
