Metadata-Version: 2.1
Name: validations-libs
Version: 1.9.0
Summary: A common library for the validations framework
Home-page: https://docs.openstack.org/validations-libs/latest/
Author: OpenStack
Author-email: openstack-discuss@lists.openstack.org
License: UNKNOWN
Platform: UNKNOWN
Classifier: Development Status :: 5 - Production/Stable
Classifier: Environment :: OpenStack
Classifier: Framework :: Ansible
Classifier: Intended Audience :: Information Technology
Classifier: Intended Audience :: System Administrators
Classifier: License :: OSI Approved :: Apache Software License
Classifier: Operating System :: POSIX :: Linux
Classifier: Programming Language :: Python
Classifier: Programming Language :: Python :: 3 :: Only
Classifier: Programming Language :: Python :: 3
Classifier: Programming Language :: Python :: 3.8
Classifier: Programming Language :: Python :: 3.9
Requires-Python: >=3.8
Requires-Dist: PyYAML (>=3.13)
Requires-Dist: ansible (!=2.8.9,!=2.9.12,<2.10.0,>=2.8)
Requires-Dist: ansible-runner (>=1.4.0)
Requires-Dist: cliff (>=2.16.0)
Requires-Dist: pbr (>=3.1.1)
Requires-Dist: six (>=1.11.0)
